CPU.py
Makefile
README.md
__init__.py
pyproject.toml
setup.py
./CPU.py
./Makefile
./__init__.py
./setup.py
./external_Pk/Pk_example.dat
./external_Pk/Pk_example_w_tensors.dat
./external_Pk/README.md
./external_Pk/generate_Pk_example.py
./external_Pk/generate_Pk_example_w_tensors.py
./include/arrays.h
./include/background.h
./include/class.h
./include/common.h
./include/dei_rkck.h
./include/evolver_ndf15.h
./include/evolver_rkck.h
./include/growTable.h
./include/hermite3_interpolation_csource.h
./include/hermite4_interpolation_csource.h
./include/hermite6_interpolation_csource.h
./include/hyperspherical.h
./include/input.h
./include/lensing.h
./include/modgrav.h
./include/nonlinear.h
./include/output.h
./include/parser.h
./include/perturbations.h
./include/precision_macros.h
./include/precisions.h
./include/primordial.h
./include/quadrature.h
./include/sparse.h
./include/spectra.h
./include/svnversion.h
./include/thermodynamics.h
./include/transfer.h
./include/trigonometric_integrals.h
./main/class.c
./python/README
./python/cclassy.pxd
./python/classy.pyx
./python/extract_errors.py
./python/interface_generator.py
./python/setup.py
./python/test_class.py
./python/test_class.pyc
./source/background.c
./source/input.c
./source/lensing.c
./source/modgrav.c
./source/nonlinear.c
./source/output.c
./source/perturbations.c
./source/primordial.c
./source/spectra.c
./source/thermodynamics.c
./source/transfer.c
./tools/arrays.c
./tools/common.c
./tools/dei_rkck.c
./tools/evolver_ndf15.c
./tools/evolver_rkck.c
./tools/growTable.c
./tools/hermite3_interpolation_csource.h
./tools/hermite4_interpolation_csource.h
./tools/hermite6_interpolation_csource.h
./tools/hyperspherical.c
./tools/parser.c
./tools/quadrature.c
./tools/sparse.c
./tools/trigonometric_integrals.c
external_Pk/Pk_example.dat
external_Pk/Pk_example_w_tensors.dat
external_Pk/README.md
external_Pk/generate_Pk_example.py
external_Pk/generate_Pk_example_w_tensors.py
include/arrays.h
include/background.h
mgclassy.egg-info/PKG-INFO
mgclassy.egg-info/SOURCES.txt
mgclassy.egg-info/dependency_links.txt
mgclassy.egg-info/not-zip-safe
mgclassy.egg-info/top_level.txt
