Metadata-Version: 2.4
Name: mgclassy
Version: 2.9.4.3
Summary: Python interface to the Cosmological Boltzmann code MGCLASS
Home-page: https://gitlab.com/zizgitlab/mgclass--ii
Author: Ziad Sakr
Project-URL: Homepage, https://gitlab.com/zizgitlab/mgclass--ii
Dynamic: home-page
